llm_benchmark/__init__.py
llm_benchmark/check_models.py
llm_benchmark/check_ollama.py
llm_benchmark/main.py
llm_benchmark/query_llm.py
llm_benchmark/run_benchmark.py
llm_benchmark/run_benchmark_one.py
llm_benchmark/data/benchmark1.yml
llm_benchmark/data/benchmark2.yml
llm_benchmark/data/benchmark_models_16gb_ram.yml
llm_benchmark/data/benchmark_models_2gb_ram.yml
llm_benchmark/data/benchmark_models_32gb_ram.yml
llm_benchmark/data/benchmark_models_3gb_ram.yml
llm_benchmark/data/benchmark_models_4gb_ram.yml
llm_benchmark/data/benchmark_models_8gb_ram.yml
llm_benchmark/data/img/sample1.jpg
llm_benchmark/data/img/sample2.jpg
llm_benchmark/data/img/sample3.jpg
llm_benchmark/data/img/sample4.jpg
llm_benchmark/data/img/sample5.jpg
llm_benchmark/security_connection/__init__.py
llm_benchmark/security_connection/connection.py
llm_benchmark/security_connection/security.py
llm_benchmark/systeminfo/__init__.py
llm_benchmark/systeminfo/sysmain.py
llm_benchmark-0.5.2.dist-info/licenses/LICENSE
llm_benchmark-0.5.2.dist-info/METADATA
llm_benchmark-0.5.2.dist-info/WHEEL
llm_benchmark-0.5.2.dist-info/entry_points.txt
llm_benchmark-0.5.2.dist-info/top_level.txt
llm_benchmark-0.5.2.dist-info/RECORD
