Metadata-Version: 2.4
Name: llm_benchmark
Version: 0.5.2
Summary: LLM Benchmark
Home-page: https://github.com/aidatatools/ollama-benchmark
Author: Jason Chuang
Author-email: chuangtcee@gmail.com
Classifier: Programming Language :: Python :: 3
Classifier: Programming Language :: Python :: 3.10
Classifier: Programming Language :: Python :: 3.11
Classifier: Programming Language :: Python :: 3.12
Classifier: Programming Language :: Python :: 3.13
Classifier: Programming Language :: Python :: 3.14
Classifier: License :: OSI Approved :: MIT License
Classifier: Operating System :: OS Independent
Requires-Python: >=3.10
License-File: LICENSE
Requires-Dist: typer==0.21.0
Requires-Dist: ollama==0.6.1
Requires-Dist: pyyaml==6.0.1
Requires-Dist: requests==2.32.4
Requires-Dist: psutil==5.9.8
Requires-Dist: GPUtil==1.4.0
Requires-Dist: lib-platform==1.2.10
Requires-Dist: setuptools==80.9.0
Dynamic: author
Dynamic: author-email
Dynamic: classifier
Dynamic: description
Dynamic: description-content-type
Dynamic: home-page
Dynamic: license-file
Dynamic: requires-dist
Dynamic: requires-python
Dynamic: summary
